{
  "_class": "shapePath",
  "booleanOperation": -1,
  "clippingMaskMode": 0,
  "do_objectID": "928BC475-EEA9-4E43-9BA4-3C91FDEE2CF0",
  "edited": true,
  "exportOptions": {
    "_class": "exportOptions",
    "exportFormats": [
    ],
    "includedLayerIds": [
    ],
    "layerOptions": 0,
    "shouldTrim": false
  },
  "frame": {
    "_class": "rect",
    "constrainProportions": false,
    "height": 12.19346733668342,
    "width": 2.873986735445831,
    "x": 7.328666175386923,
    "y": 2.484924623115552
  },
  "hasClippingMask": false,
  "isClosed": true,
  "isFixedToViewport": false,
  "isFlippedHorizontal": false,
  "isFlippedVertical": false,
  "isLocked": false,
  "isVisible": true,
  "layerListExpandedType": 0,
  "name": "Path",
  "nameIsFixed": false,
  "pointRadiusBehaviour": 1,
  "points": [
    {
      "_class": "curvePoint",
      "cornerRadius": 0,
      "curveFrom": "{1, 0.11374407582938419}",
      "curveMode": 1,
      "curveTo": "{1, 0.11374407582938419}",
      "hasCurveFrom": false,
      "hasCurveTo": false,
      "point": "{1, 0.11374407582938419}"
    },
    {
      "_class": "curvePoint",
      "cornerRadius": 0,
      "curveFrom": "{0.47000000000000453, 0}",
      "curveMode": 1,
      "curveTo": "{0.47000000000000453, 0}",
      "hasCurveFrom": false,
      "hasCurveTo": false,
      "point": "{0.47000000000000453, 0}"
    },
    {
      "_class": "curvePoint",
      "cornerRadius": 0,
      "curveFrom": "{0, 0.11848341232227491}",
      "curveMode": 1,
      "curveTo": "{0, 0.11848341232227491}",
      "hasCurveFrom": false,
      "hasCurveTo": false,
      "point": "{0, 0.11848341232227491}"
    },
    {
      "_class": "curvePoint",
      "cornerRadius": 0,
      "curveFrom": "{0.42000000000000454, 0.90047393364928929}",
      "curveMode": 4,
      "curveTo": "{0, 0.88862559241706185}",
      "hasCurveFrom": true,
      "hasCurveTo": false,
      "point": "{0, 0.88862559241706185}"
    },
    {
      "_class": "curvePoint",
      "cornerRadius": 0,
      "curveFrom": "{0.98999999999999777, 1}",
      "curveMode": 4,
      "curveTo": "{0.72999999999999543, 0.93601895734597185}",
      "hasCurveFrom": false,
      "hasCurveTo": true,
      "point": "{0.98999999999999777, 1}"
    },
    {
      "_class": "curvePoint",
      "cornerRadius": 0,
      "curveFrom": "{1, 0.99763033175355398}",
      "curveMode": 1,
      "curveTo": "{1, 0.99763033175355398}",
      "hasCurveFrom": false,
      "hasCurveTo": false,
      "point": "{1, 0.99763033175355398}"
    }
  ],
  "resizingConstraint": 63,
  "resizingType": 0,
  "rotation": 0,
  "shouldBreakMaskChain": false,
  "style": {
    "_class": "style",
    "blur": {
      "_class": "blur",
      "center": "{0.5, 0.5}",
      "isEnabled": false,
      "motionAngle": 0,
      "radius": 10,
      "saturation": 1,
      "type": 0
    },
    "borderOptions": {
      "_class": "borderOptions",
      "dashPattern": [
      ],
      "isEnabled": true,
      "lineCapStyle": 0,
      "lineJoinStyle": 0
    },
    "borders": [
    ],
    "colorControls": {
      "_class": "colorControls",
      "brightness": 0,
      "contrast": 1,
      "hue": 0,
      "isEnabled": false,
      "saturation": 1
    },
    "contextSettings": {
      "_class": "graphicsContextSettings",
      "blendMode": 0,
      "opacity": 1
    },
    "do_objectID": "8092E9A2-34F0-48F6-9D39-C0F2C086491B",
    "endMarkerType": 0,
    "fills": [
    ],
    "innerShadows": [
    ],
    "miterLimit": 10,
    "shadows": [
    ],
    "startMarkerType": 0,
    "windingRule": 1
  }
}